mpmg/__init__.py
mpmg/mpmg_env.py
mpmg-0.2.4.dist-info/LICENSE
mpmg-0.2.4.dist-info/METADATA
mpmg-0.2.4.dist-info/WHEEL
mpmg-0.2.4.dist-info/top_level.txt
mpmg-0.2.4.dist-info/RECORD
