Metadata-Version: 2.1
Name: mpmg
Version: 0.2.4
Summary: A Minimum Price Markov Game modular environment
Home-page: https://github.com/IgorSadoune/mpmg-python-package
Author: Igor Sadoune
Author-email: igor.sadoune@polymtl.ca
License: MIT
Platform: UNKNOWN
Classifier: Development Status :: 3 - Alpha
Classifier: Intended Audience :: Science/Research
Classifier: Topic :: Software Development :: Libraries
Classifier: Programming Language :: Python :: 3
Classifier: License :: OSI Approved :: MIT License
Requires-Python: >=3.10.12
License-File: LICENSE
Requires-Dist: numpy
